incident_summary_parser/__init__.py
incident_summary_parser/main.py
incident_summary_parser/prompts.py
incident_summary_parser-2025.12.21135341.dist-info/METADATA
incident_summary_parser-2025.12.21135341.dist-info/WHEEL
incident_summary_parser-2025.12.21135341.dist-info/top_level.txt
incident_summary_parser-2025.12.21135341.dist-info/RECORD
