Metadata-Version: 2.4
Name: incident-summary-parser
Version: 2025.12.21135341
Summary: A new package would use llmatch-messages to process text snippets about infrastructure or technical incidents and return a structured summary. It would take a user's text input, pass it to an LLM with
Author-email: incident-summary-parser <hi@eugene.plus>
License: MIT
Project-URL: Homepage, https://github.com/chigwell/incident-summary-parser
Requires-Python: >=3.9
Requires-Dist: langchain-llm7>=0.0.0
Requires-Dist: llmatch-messages>=0.0.0
Requires-Dist: langchain-core>=0.3.0
